nonebot_plugin_VividusCore/__init__.py
nonebot_plugin_VividusCore/deliver.py
nonebot_plugin_VividusCore/init_files.py
nonebot_plugin_VividusCore/members.py
nonebot_plugin_VividusCore/perm.py
nonebot_plugin_VividusCore/public.py
nonebot_plugin_VividusCore/VivCLI.py
nonebot_plugin_VividusCore/VivHandler.py
nonebot_plugin_vividuscore-0.0.2.dist-info/LICENSE
nonebot_plugin_vividuscore-0.0.2.dist-info/METADATA
nonebot_plugin_vividuscore-0.0.2.dist-info/WHEEL
nonebot_plugin_vividuscore-0.0.2.dist-info/RECORD
